skcv/__init__.py
skcv/core.py
skcv/filters.py
skcv_toolkit-0.1.0.dist-info/METADATA
skcv_toolkit-0.1.0.dist-info/WHEEL
skcv_toolkit-0.1.0.dist-info/top_level.txt
skcv_toolkit-0.1.0.dist-info/RECORD
